inventree_forecasting/__init__.py
inventree_forecasting/core.py
inventree_forecasting/serializers.py
inventree_forecasting/views.py
inventree_forecasting/static/ForecastingPanel.js
inventree_forecasting/static/ForecastingPanel.js.map
inventree_forecasting/static/.vite/manifest.json
inventree_stock_forecasting-0.4.2.dist-info/licenses/LICENSE
inventree_stock_forecasting-0.4.2.dist-info/METADATA
inventree_stock_forecasting-0.4.2.dist-info/WHEEL
inventree_stock_forecasting-0.4.2.dist-info/entry_points.txt
inventree_stock_forecasting-0.4.2.dist-info/top_level.txt
inventree_stock_forecasting-0.4.2.dist-info/RECORD
